bip380/__init__.py
bip380/key.py
bip380/descriptors/__init__.py
bip380/descriptors/checksum.py
bip380/descriptors/errors.py
bip380/descriptors/parsing.py
bip380/miniscript/__init__.py
bip380/miniscript/errors.py
bip380/miniscript/fragments.py
bip380/miniscript/parsing.py
bip380/miniscript/property.py
bip380/miniscript/satisfaction.py
bip380/utils/__init__.py
bip380/utils/bignum.py
bip380/utils/hashes.py
bip380/utils/script.py
bip380-0.0.3.dist-info/LICENSE
bip380-0.0.3.dist-info/METADATA
bip380-0.0.3.dist-info/WHEEL
bip380-0.0.3.dist-info/top_level.txt
bip380-0.0.3.dist-info/RECORD
