Metadata-Version: 2.1
Name: bip380
Version: 0.0.3
Summary: Bitcoin Output Script Descriptors (with Miniscript)
Home-page: http://github.com/darosior/python-bip380
Author: Antoine Poinsot
Author-email: darosior@protonmail.com
License: MIT
Keywords: bitcoin,miniscript,script,descriptor
Platform: UNKNOWN
Requires-Dist: bip32 (~=3.0)
